CHANGES.rst
DESCRIPTION.rst
LICENSE
MANIFEST.in
README.md
setup.py
src/ldc_openai/__init__.py
src/ldc_openai/class_lister.py
src/ldc_openai.egg-info/PKG-INFO
src/ldc_openai.egg-info/SOURCES.txt
src/ldc_openai.egg-info/dependency_links.txt
src/ldc_openai.egg-info/entry_points.txt
src/ldc_openai.egg-info/requires.txt
src/ldc_openai.egg-info/top_level.txt
src/ldc_openai/filter/__init__.py
src/ldc_openai/filter/_openai_count_tokens.py