Metadata-Version: 2.1
Name: ldc-openai
Version: 0.0.2
Summary: Python3 library containing plugins for llm-dataset-converter specific to OpenAI.
Home-page: https://github.com/waikato-llm/ldc-openai
Author: Peter Reutemann
Author-email: fracpete@waikato.ac.nz
License: MIT License
Classifier: Development Status :: 4 - Beta
Classifier: License :: OSI Approved :: MIT License
Classifier: Topic :: Scientific/Engineering :: Artificial Intelligence
Classifier: Programming Language :: Python :: 3
License-File: LICENSE
